sklearn_fluent/__init__.py
sklearn_fluent/main.py
sklearn_fluent-0.5.0.dist-info/METADATA
sklearn_fluent-0.5.0.dist-info/WHEEL
sklearn_fluent-0.5.0.dist-info/top_level.txt
sklearn_fluent-0.5.0.dist-info/RECORD
